CHANGES.txt
LICENSE.txt
MANIFEST.in
README.txt
setup.py
js/__init__.py
js.jquery_tablesorter.egg-info/PKG-INFO
js.jquery_tablesorter.egg-info/SOURCES.txt
js.jquery_tablesorter.egg-info/dependency_links.txt
js.jquery_tablesorter.egg-info/entry_points.txt
js.jquery_tablesorter.egg-info/namespace_packages.txt
js.jquery_tablesorter.egg-info/not-zip-safe
js.jquery_tablesorter.egg-info/requires.txt
js.jquery_tablesorter.egg-info/top_level.txt
js/jquery_tablesorter/__init__.py
js/jquery_tablesorter/test_jquery_tablesorter.txt
js/jquery_tablesorter/resources/jquery.tablesorter.js
js/jquery_tablesorter/resources/jquery.tablesorter.min.js
js/jquery_tablesorter/resources/addons/pager/jquery.tablesorter.pager.css
js/jquery_tablesorter/resources/addons/pager/jquery.tablesorter.pager.js
js/jquery_tablesorter/resources/themes/blue/asc.gif
js/jquery_tablesorter/resources/themes/blue/bg.gif
js/jquery_tablesorter/resources/themes/blue/desc.gif
js/jquery_tablesorter/resources/themes/blue/style.css
js/jquery_tablesorter/resources/themes/green/asc.png
js/jquery_tablesorter/resources/themes/green/bg.png
js/jquery_tablesorter/resources/themes/green/desc.png
js/jquery_tablesorter/resources/themes/green/style.css