Metadata-Version: 1.0
Name: js.jquery-tablesorter
Version: 2.0.5
Summary: Fanstatic packaging of jQuery tablesorter
Home-page: UNKNOWN
Author: Fanstatic Developers
Author-email: fanstatic@googlegroups.com
License: BSD
Platform: UNKNOWN
